cietools/__init__.py
cietools/__init__.pyi
cietools/_cietools_c_ext.cpython-313-darwin.so
cietools/py.typed
cietools-0.3.1.dist-info/LICENSE
cietools-0.3.1.dist-info/METADATA
cietools-0.3.1.dist-info/WHEEL
cietools-0.3.1.dist-info/top_level.txt
cietools-0.3.1.dist-info/RECORD
