Metadata-Version: 2.2
Name: cietools
Version: 0.3.1
Summary: A C-based python library to convert CIE formats/calculate Delta E
Author: ItzSkyReed
License: CC-BY-4.0
Project-URL: Homepage, https://github.com/ItzSkyReed/CIETools
Classifier: Development Status :: 4 - Beta
Classifier: Programming Language :: Python :: 3.12
Classifier: Programming Language :: Python :: 3.13
Classifier: Operating System :: POSIX :: Linux
Classifier: Operating System :: MacOS
Classifier: Operating System :: Microsoft :: Windows
Requires-Python: >=3.13
License-File: LICENSE
Requires-Dist: wheel
Requires-Dist: setuptools
